Metadata-Version: 1.0
Name: gode
Version: 1.4
Summary: Gaussian and Binomial distributions
Home-page: UNKNOWN
Author: andiwolih
Author-email: abdiwolih@gmail.com
License: UNKNOWN
Platform: UNKNOWN
